setup.py
responsivetone.egg-info/PKG-INFO
responsivetone.egg-info/SOURCES.txt
responsivetone.egg-info/dependency_links.txt
responsivetone.egg-info/top_level.txt
rest/__init__.py
rest/rest.py
restmlask/__init__.py
restmlask/restmlask.py
resttweet/__init__.py
resttweet/resttweet.py
restwin/__init__.py
restwin/voiceroid.py